brick_tq_shacl/__init__.py
brick_tq_shacl-0.4.0.dist-info/METADATA
brick_tq_shacl-0.4.0.dist-info/WHEEL
brick_tq_shacl-0.4.0.dist-info/licenses/LICENSE
brick_tq_shacl-0.4.0.dist-info/RECORD
