Metadata-Version: 2.4
Name: brick-tq-shacl
Version: 0.4.0
Summary: Wraps topquadrant's SHACL implementation in a simple Python wrapper to be API-compatible with pySHACL
Author-email: Gabe Fierro <gtfierro@mines.edu>
License-Expression: BSD-3-Clause
License-File: LICENSE
Requires-Python: <4.0,>=3.9
Requires-Dist: pyontoenv>=0.3.1a1
Requires-Dist: pytqshacl>=140
Requires-Dist: rdflib>=7.0
